{
  "description": "",
  "entries": [
    {
      "type": "creative_labs_audio",
      "game": "LBA1",
      "description": "Principal Island voice for text 0"
    },
    {
      "type": "creative_labs_audio",
      "game": "LBA1",
      "description": "Principal Island voice for text 1"
    },
    {
      "type": "creative_labs_audio",
      "game": "LBA1",
      "description": "Principal Island voice for text 2"
    },
    {
      "type": "creative_labs_audio",
      "game": "LBA1",
      "description": "Principal Island voice for text 3"
    },
    {
      "type": "creative_labs_audio",
      "game": "LBA1",
      "description": "Principal Island voice for text 4"
    },
    {
      "type": "creative_labs_audio",
      "game": "LBA1",
      "description": "Principal Island voice for text 5"
    },
    {
      "type": "creative_labs_audio",
      "game": "LBA1",
      "description": "Principal Island voice for text 6"
    },
    {
      "type": "creative_labs_audio",
      "game": "LBA1",
      "description": "Principal Island voice for text 7"
    },
    {
      "type": "creative_labs_audio",
      "game": "LBA1",
      "description": "Principal Island voice for text 8"
    },
    {
      "type": "creative_labs_audio",
      "game": "LBA1",
      "description": "Principal Island voice for text 9"
    },
    {
      "type": "creative_labs_audio",
      "game": "LBA1",
      "description": "Principal Island voice for text 10"
    },
    {
      "type": "creative_labs_audio",
      "game": "LBA1",
      "description": "Principal Island voice for text 11"
    },
    {
      "type": "creative_labs_audio",
      "game": "LBA1",
      "description": "Principal Island voice for text 12"
    },
    {
      "type": "creative_labs_audio",
      "game": "LBA1",
      "description": "Principal Island voice for text 13"
    },
    {
      "type": "creative_labs_audio",
      "game": "LBA1",
      "description": "Principal Island voice for text 14"
    },
    {
      "type": "creative_labs_audio",
      "game": "LBA1",
      "description": "Principal Island voice for text 15"
    },
    {
      "type": "creative_labs_audio",
      "game": "LBA1",
      "description": "Principal Island voice for text 16"
    },
    {
      "type": "creative_labs_audio",
      "game": "LBA1",
      "description": "Principal Island voice for text 17"
    },
    {
      "type": "creative_labs_audio",
      "game": "LBA1",
      "description": "Principal Island voice for text 18"
    },
    {
      "type": "creative_labs_audio",
      "game": "LBA1",
      "description": "Principal Island voice for text 19"
    },
    {
      "type": "creative_labs_audio",
      "game": "LBA1",
      "description": "Principal Island voice for text 20"
    },
    {
      "type": "creative_labs_audio",
      "game": "LBA1",
      "description": "Principal Island voice for text 21"
    },
    {
      "type": "creative_labs_audio",
      "game": "LBA1",
      "description": "Principal Island voice for text 22"
    },
    {
      "type": "creative_labs_audio",
      "game": "LBA1",
      "description": "Principal Island voice for text 23"
    },
    {
      "type": "creative_labs_audio",
      "game": "LBA1",
      "description": "Principal Island voice for text 24"
    },
    {
      "type": "creative_labs_audio",
      "game": "LBA1",
      "description": "Principal Island voice for text 25"
    },
    {
      "type": "creative_labs_audio",
      "game": "LBA1",
      "description": "Principal Island voice for text 26"
    },
    {
      "type": "creative_labs_audio",
      "game": "LBA1",
      "description": "Principal Island voice for text 27"
    },
    {
      "type": "creative_labs_audio",
      "game": "LBA1",
      "description": "Principal Island voice for text 28"
    },
    {
      "type": "creative_labs_audio",
      "game": "LBA1",
      "description": "Principal Island voice for text 29"
    },
    {
      "type": "creative_labs_audio",
      "game": "LBA1",
      "description": "Principal Island voice for text 30"
    },
    {
      "type": "creative_labs_audio",
      "game": "LBA1",
      "description": "Principal Island voice for text 31"
    },
    {
      "type": "creative_labs_audio",
      "game": "LBA1",
      "description": "Principal Island voice for text 32"
    },
    {
      "type": "creative_labs_audio",
      "game": "LBA1",
      "description": "Principal Island voice for text 33"
    },
    {
      "type": "creative_labs_audio",
      "game": "LBA1",
      "description": "Principal Island voice for text 34"
    },
    {
      "type": "creative_labs_audio",
      "game": "LBA1",
      "description": "Principal Island voice for text 35"
    },
    {
      "type": "creative_labs_audio",
      "game": "LBA1",
      "description": "Principal Island voice for text 36"
    },
    {
      "type": "creative_labs_audio",
      "game": "LBA1",
      "description": "Principal Island voice for text 37"
    },
    {
      "type": "creative_labs_audio",
      "game": "LBA1",
      "description": "Principal Island voice for text 38"
    },
    {
      "type": "creative_labs_audio",
      "game": "LBA1",
      "description": "Principal Island voice for text 39"
    },
    {
      "type": "creative_labs_audio",
      "game": "LBA1",
      "description": "Principal Island voice for text 40"
    },
    {
      "type": "creative_labs_audio",
      "game": "LBA1",
      "description": "Principal Island voice for text 41"
    },
    {
      "type": "creative_labs_audio",
      "game": "LBA1",
      "description": "Principal Island voice for text 42"
    },
    {
      "type": "creative_labs_audio",
      "game": "LBA1",
      "description": "Principal Island voice for text 43"
    },
    {
      "type": "creative_labs_audio",
      "game": "LBA1",
      "description": "Principal Island voice for text 44"
    },
    {
      "type": "creative_labs_audio",
      "game": "LBA1",
      "description": "Principal Island voice for text 45"
    },
    {
      "type": "creative_labs_audio",
      "game": "LBA1",
      "description": "Principal Island voice for text 46"
    },
    {
      "type": "creative_labs_audio",
      "game": "LBA1",
      "description": "Principal Island voice for text 47"
    },
    {
      "type": "creative_labs_audio",
      "game": "LBA1",
      "description": "Principal Island voice for text 48"
    },
    {
      "type": "creative_labs_audio",
      "game": "LBA1",
      "description": "Principal Island voice for text 49"
    },
    {
      "type": "creative_labs_audio",
      "game": "LBA1",
      "description": "Principal Island voice for text 50"
    },
    {
      "type": "creative_labs_audio",
      "game": "LBA1",
      "description": "Principal Island voice for text 51"
    },
    {
      "type": "creative_labs_audio",
      "game": "LBA1",
      "description": "Principal Island voice for text 52"
    },
    {
      "type": "creative_labs_audio",
      "game": "LBA1",
      "description": "Principal Island voice for text 53"
    },
    {
      "type": "creative_labs_audio",
      "game": "LBA1",
      "description": "Principal Island voice for text 54"
    },
    {
      "type": "creative_labs_audio",
      "game": "LBA1",
      "description": "Principal Island voice for text 55"
    },
    {
      "type": "creative_labs_audio",
      "game": "LBA1",
      "description": "Principal Island voice for text 56"
    },
    {
      "type": "creative_labs_audio",
      "game": "LBA1",
      "description": "Principal Island voice for text 57"
    },
    {
      "type": "creative_labs_audio",
      "game": "LBA1",
      "description": "Principal Island voice for text 58"
    },
    {
      "type": "creative_labs_audio",
      "game": "LBA1",
      "description": "Principal Island voice for text 59"
    },
    {
      "type": "creative_labs_audio",
      "game": "LBA1",
      "description": "Principal Island voice for text 60"
    },
    {
      "type": "creative_labs_audio",
      "game": "LBA1",
      "description": "Principal Island voice for text 61"
    },
    {
      "type": "creative_labs_audio",
      "game": "LBA1",
      "description": "Principal Island voice for text 62"
    },
    {
      "type": "creative_labs_audio",
      "game": "LBA1",
      "description": "Principal Island voice for text 63"
    },
    {
      "type": "creative_labs_audio",
      "game": "LBA1",
      "description": "Principal Island voice for text 64"
    },
    {
      "type": "creative_labs_audio",
      "game": "LBA1",
      "description": "Principal Island voice for text 65"
    },
    {
      "type": "creative_labs_audio",
      "game": "LBA1",
      "description": "Principal Island voice for text 66"
    },
    {
      "type": "creative_labs_audio",
      "game": "LBA1",
      "description": "Principal Island voice for text 67"
    },
    {
      "type": "creative_labs_audio",
      "game": "LBA1",
      "description": "Principal Island voice for text 68"
    },
    {
      "type": "creative_labs_audio",
      "game": "LBA1",
      "description": "Principal Island voice for text 69"
    },
    {
      "type": "creative_labs_audio",
      "game": "LBA1",
      "description": "Principal Island voice for text 70"
    },
    {
      "type": "creative_labs_audio",
      "game": "LBA1",
      "description": "Principal Island voice for text 71"
    },
    {
      "type": "creative_labs_audio",
      "game": "LBA1",
      "description": "Principal Island voice for text 72"
    },
    {
      "type": "creative_labs_audio",
      "game": "LBA1",
      "description": "Principal Island voice for text 73"
    },
    {
      "type": "creative_labs_audio",
      "game": "LBA1",
      "description": "Principal Island voice for text 74"
    },
    {
      "type": "creative_labs_audio",
      "game": "LBA1",
      "description": "Principal Island voice for text 75"
    },
    {
      "type": "creative_labs_audio",
      "game": "LBA1",
      "description": "Principal Island voice for text 76"
    },
    {
      "type": "creative_labs_audio",
      "game": "LBA1",
      "description": "Principal Island voice for text 77"
    },
    {
      "type": "creative_labs_audio",
      "game": "LBA1",
      "description": "Principal Island voice for text 78"
    },
    {
      "type": "creative_labs_audio",
      "game": "LBA1",
      "description": "Principal Island voice for text 79"
    },
    {
      "type": "creative_labs_audio",
      "game": "LBA1",
      "description": "Principal Island voice for text 80"
    },
    {
      "type": "creative_labs_audio",
      "game": "LBA1",
      "description": "Principal Island voice for text 81"
    },
    {
      "type": "creative_labs_audio",
      "game": "LBA1",
      "description": "Principal Island voice for text 82"
    },
    {
      "type": "creative_labs_audio",
      "game": "LBA1",
      "description": "Principal Island voice for text 83"
    },
    {
      "type": "creative_labs_audio",
      "game": "LBA1",
      "description": "Principal Island voice for text 84"
    },
    {
      "type": "creative_labs_audio",
      "game": "LBA1",
      "description": "Principal Island voice for text 85"
    },
    {
      "type": "creative_labs_audio",
      "game": "LBA1",
      "description": "Principal Island voice for text 86"
    },
    {
      "type": "creative_labs_audio",
      "game": "LBA1",
      "description": "Principal Island voice for text 87"
    },
    {
      "type": "creative_labs_audio",
      "game": "LBA1",
      "description": "Principal Island voice for text 88"
    },
    {
      "type": "creative_labs_audio",
      "game": "LBA1",
      "description": "Principal Island voice for text 89"
    },
    {
      "type": "creative_labs_audio",
      "game": "LBA1",
      "description": "Principal Island voice for text 90"
    },
    {
      "type": "creative_labs_audio",
      "game": "LBA1",
      "description": "Principal Island voice for text 91"
    },
    {
      "type": "creative_labs_audio",
      "game": "LBA1",
      "description": "Principal Island voice for text 92"
    },
    {
      "type": "creative_labs_audio",
      "game": "LBA1",
      "description": "Principal Island voice for text 93"
    },
    {
      "type": "creative_labs_audio",
      "game": "LBA1",
      "description": "Principal Island voice for text 94"
    },
    {
      "type": "creative_labs_audio",
      "game": "LBA1",
      "description": "Principal Island voice for text 95"
    },
    {
      "type": "creative_labs_audio",
      "game": "LBA1",
      "description": "Principal Island voice for text 96"
    },
    {
      "type": "creative_labs_audio",
      "game": "LBA1",
      "description": "Principal Island voice for text 97"
    },
    {
      "type": "creative_labs_audio",
      "game": "LBA1",
      "description": "Principal Island voice for text 98"
    },
    {
      "type": "creative_labs_audio",
      "game": "LBA1",
      "description": "Principal Island voice for text 99"
    },
    {
      "type": "creative_labs_audio",
      "game": "LBA1",
      "description": "Principal Island voice for text 100"
    },
    {
      "type": "creative_labs_audio",
      "game": "LBA1",
      "description": "Principal Island voice for text 101"
    },
    {
      "type": "creative_labs_audio",
      "game": "LBA1",
      "description": "Principal Island voice for text 102"
    },
    {
      "type": "creative_labs_audio",
      "game": "LBA1",
      "description": "Principal Island voice for text 103"
    },
    {
      "type": "creative_labs_audio",
      "game": "LBA1",
      "description": "Principal Island voice for text 104"
    },
    {
      "type": "creative_labs_audio",
      "game": "LBA1",
      "description": "Principal Island voice for text 105"
    },
    {
      "type": "creative_labs_audio",
      "game": "LBA1",
      "description": "Principal Island voice for text 106"
    },
    {
      "type": "creative_labs_audio",
      "game": "LBA1",
      "description": "Principal Island voice for text 107"
    },
    {
      "type": "creative_labs_audio",
      "game": "LBA1",
      "description": "Principal Island voice for text 108"
    },
    {
      "type": "creative_labs_audio",
      "game": "LBA1",
      "description": "Principal Island voice for text 109"
    },
    {
      "type": "creative_labs_audio",
      "game": "LBA1",
      "description": "Principal Island voice for text 110"
    },
    {
      "type": "creative_labs_audio",
      "game": "LBA1",
      "description": "Principal Island voice for text 111"
    },
    {
      "type": "creative_labs_audio",
      "game": "LBA1",
      "description": "Principal Island voice for text 112"
    },
    {
      "type": "creative_labs_audio",
      "game": "LBA1",
      "description": "Principal Island voice for text 113"
    },
    {
      "type": "creative_labs_audio",
      "game": "LBA1",
      "description": "Principal Island voice for text 114"
    },
    {
      "type": "creative_labs_audio",
      "game": "LBA1",
      "description": "Principal Island voice for text 115"
    },
    {
      "type": "creative_labs_audio",
      "game": "LBA1",
      "description": "Principal Island voice for text 116"
    },
    {
      "type": "creative_labs_audio",
      "game": "LBA1",
      "description": "Principal Island voice for text 117"
    },
    {
      "type": "creative_labs_audio",
      "game": "LBA1",
      "description": "Principal Island voice for text 118"
    },
    {
      "type": "creative_labs_audio",
      "game": "LBA1",
      "description": "Principal Island voice for text 119"
    },
    {
      "type": "creative_labs_audio",
      "game": "LBA1",
      "description": "Principal Island voice for text 120"
    },
    {
      "type": "creative_labs_audio",
      "game": "LBA1",
      "description": "Principal Island voice for text 121"
    },
    {
      "type": "creative_labs_audio",
      "game": "LBA1",
      "description": "Principal Island voice for text 122"
    },
    {
      "type": "creative_labs_audio",
      "game": "LBA1",
      "description": "Principal Island voice for text 123"
    },
    {
      "type": "creative_labs_audio",
      "game": "LBA1",
      "description": "Principal Island voice for text 124"
    },
    {
      "type": "creative_labs_audio",
      "game": "LBA1",
      "description": "Principal Island voice for text 125"
    },
    {
      "type": "creative_labs_audio",
      "game": "LBA1",
      "description": "Principal Island voice for text 126"
    },
    {
      "type": "creative_labs_audio",
      "game": "LBA1",
      "description": "Principal Island voice for text 127"
    },
    {
      "type": "creative_labs_audio",
      "game": "LBA1",
      "description": "Principal Island voice for text 128"
    },
    {
      "type": "creative_labs_audio",
      "game": "LBA1",
      "description": "Principal Island voice for text 129"
    },
    {
      "type": "creative_labs_audio",
      "game": "LBA1",
      "description": "Principal Island voice for text 130"
    },
    {
      "type": "creative_labs_audio",
      "game": "LBA1",
      "description": "Principal Island voice for text 131"
    },
    {
      "type": "creative_labs_audio",
      "game": "LBA1",
      "description": "Principal Island voice for text 132"
    },
    {
      "type": "creative_labs_audio",
      "game": "LBA1",
      "description": "Principal Island voice for text 133"
    },
    {
      "type": "creative_labs_audio",
      "game": "LBA1",
      "description": "Principal Island voice for text 134"
    },
    {
      "type": "creative_labs_audio",
      "game": "LBA1",
      "description": "Principal Island voice for text 135"
    },
    {
      "type": "creative_labs_audio",
      "game": "LBA1",
      "description": "Principal Island voice for text 136"
    },
    {
      "type": "creative_labs_audio",
      "game": "LBA1",
      "description": "Principal Island voice for text 137"
    },
    {
      "type": "creative_labs_audio",
      "game": "LBA1",
      "description": "Principal Island voice for text 138"
    },
    {
      "type": "creative_labs_audio",
      "game": "LBA1",
      "description": "Principal Island voice for text 139"
    },
    {
      "type": "creative_labs_audio",
      "game": "LBA1",
      "description": "Principal Island voice for text 140"
    },
    {
      "type": "creative_labs_audio",
      "game": "LBA1",
      "description": "Principal Island voice for text 141"
    },
    {
      "type": "creative_labs_audio",
      "game": "LBA1",
      "description": "Principal Island voice for text 142"
    },
    {
      "type": "creative_labs_audio",
      "game": "LBA1",
      "description": "Principal Island voice for text 143"
    },
    {
      "type": "creative_labs_audio",
      "game": "LBA1",
      "description": "Principal Island voice for text 144"
    },
    {
      "type": "creative_labs_audio",
      "game": "LBA1",
      "description": "Principal Island voice for text 145"
    },
    {
      "type": "creative_labs_audio",
      "game": "LBA1",
      "description": "Principal Island voice for text 146"
    },
    {
      "type": "creative_labs_audio",
      "game": "LBA1",
      "description": "Principal Island voice for text 147"
    },
    {
      "type": "creative_labs_audio",
      "game": "LBA1",
      "description": "Principal Island voice for text 148"
    },
    {
      "type": "creative_labs_audio",
      "game": "LBA1",
      "description": "Principal Island voice for text 149"
    },
    {
      "type": "creative_labs_audio",
      "game": "LBA1",
      "description": "Principal Island voice for text 150"
    },
    {
      "type": "creative_labs_audio",
      "game": "LBA1",
      "description": "Principal Island voice for text 151"
    },
    {
      "type": "creative_labs_audio",
      "game": "LBA1",
      "description": "Principal Island voice for text 152"
    },
    {
      "type": "creative_labs_audio",
      "game": "LBA1",
      "description": "Principal Island voice for text 153"
    },
    {
      "type": "creative_labs_audio",
      "game": "LBA1",
      "description": "Principal Island voice for text 154"
    },
    {
      "type": "creative_labs_audio",
      "game": "LBA1",
      "description": "Principal Island voice for text 155"
    },
    {
      "type": "creative_labs_audio",
      "game": "LBA1",
      "description": "Principal Island voice for text 156"
    },
    {
      "type": "creative_labs_audio",
      "game": "LBA1",
      "description": "Principal Island voice for text 157"
    },
    {
      "type": "creative_labs_audio",
      "game": "LBA1",
      "description": "Principal Island voice for text 158"
    },
    {
      "type": "creative_labs_audio",
      "game": "LBA1",
      "description": "Principal Island voice for text 159"
    },
    {
      "type": "creative_labs_audio",
      "game": "LBA1",
      "description": "Principal Island voice for text 160"
    },
    {
      "type": "creative_labs_audio",
      "game": "LBA1",
      "description": "Principal Island voice for text 161"
    },
    {
      "type": "creative_labs_audio",
      "game": "LBA1",
      "description": "Principal Island voice for text 162"
    },
    {
      "type": "creative_labs_audio",
      "game": "LBA1",
      "description": "Principal Island voice for text 163"
    },
    {
      "type": "creative_labs_audio",
      "game": "LBA1",
      "description": "Principal Island voice for text 164"
    },
    {
      "type": "creative_labs_audio",
      "game": "LBA1",
      "description": "Principal Island voice for text 165"
    },
    {
      "type": "creative_labs_audio",
      "game": "LBA1",
      "description": "Principal Island voice for text 166"
    },
    {
      "type": "creative_labs_audio",
      "game": "LBA1",
      "description": "Principal Island voice for text 167"
    },
    {
      "type": "creative_labs_audio",
      "game": "LBA1",
      "description": "Principal Island voice for text 168"
    },
    {
      "type": "creative_labs_audio",
      "game": "LBA1",
      "description": "Principal Island voice for text 169"
    },
    {
      "type": "creative_labs_audio",
      "game": "LBA1",
      "description": "Principal Island voice for text 170"
    },
    {
      "type": "creative_labs_audio",
      "game": "LBA1",
      "description": "Principal Island voice for text 171"
    },
    {
      "type": "creative_labs_audio",
      "game": "LBA1",
      "description": "Principal Island voice for text 172"
    },
    {
      "type": "creative_labs_audio",
      "game": "LBA1",
      "description": "Principal Island voice for text 173"
    },
    {
      "type": "creative_labs_audio",
      "game": "LBA1",
      "description": "Principal Island voice for text 174"
    },
    {
      "type": "creative_labs_audio",
      "game": "LBA1",
      "description": "Principal Island voice for text 175"
    },
    {
      "type": "creative_labs_audio",
      "game": "LBA1",
      "description": "Principal Island voice for text 176"
    },
    {
      "type": "creative_labs_audio",
      "game": "LBA1",
      "description": "Principal Island voice for text 177"
    },
    {
      "type": "creative_labs_audio",
      "game": "LBA1",
      "description": "Principal Island voice for text 178"
    },
    {
      "type": "creative_labs_audio",
      "game": "LBA1",
      "description": "Principal Island voice for text 179"
    },
    {
      "type": "creative_labs_audio",
      "game": "LBA1",
      "description": "Principal Island voice for text 180"
    },
    {
      "type": "creative_labs_audio",
      "game": "LBA1",
      "description": "Principal Island voice for text 181"
    },
    {
      "type": "creative_labs_audio",
      "game": "LBA1",
      "description": "Principal Island voice for text 182"
    },
    {
      "type": "creative_labs_audio",
      "game": "LBA1",
      "description": "Principal Island voice for text 183"
    },
    {
      "type": "creative_labs_audio",
      "game": "LBA1",
      "description": "Principal Island voice for text 184"
    },
    {
      "type": "creative_labs_audio",
      "game": "LBA1",
      "description": "Principal Island voice for text 185"
    },
    {
      "type": "creative_labs_audio",
      "game": "LBA1",
      "description": "Principal Island voice for text 186"
    },
    {
      "type": "creative_labs_audio",
      "game": "LBA1",
      "description": "Principal Island voice for text 187"
    },
    {
      "type": "creative_labs_audio",
      "game": "LBA1",
      "description": "Principal Island voice for text 188"
    },
    {
      "type": "creative_labs_audio",
      "game": "LBA1",
      "description": "Principal Island voice for text 189"
    },
    {
      "type": "creative_labs_audio",
      "game": "LBA1",
      "description": "Principal Island voice for text 190"
    },
    {
      "type": "creative_labs_audio",
      "game": "LBA1",
      "description": "Principal Island voice for text 191"
    },
    {
      "type": "creative_labs_audio",
      "game": "LBA1",
      "description": "Principal Island voice for text 192"
    },
    {
      "type": "creative_labs_audio",
      "game": "LBA1",
      "description": "Principal Island voice for text 193"
    },
    {
      "type": "creative_labs_audio",
      "game": "LBA1",
      "description": "Principal Island voice for text 194"
    },
    {
      "type": "creative_labs_audio",
      "game": "LBA1",
      "description": "Principal Island voice for text 195"
    },
    {
      "type": "creative_labs_audio",
      "game": "LBA1",
      "description": "Principal Island voice for text 196"
    },
    {
      "type": "creative_labs_audio",
      "game": "LBA1",
      "description": "Principal Island voice for text 197"
    },
    {
      "type": "creative_labs_audio",
      "game": "LBA1",
      "description": "Principal Island voice for text 198"
    },
    {
      "type": "creative_labs_audio",
      "game": "LBA1",
      "description": "Principal Island voice for text 199"
    },
    {
      "type": "creative_labs_audio",
      "game": "LBA1",
      "description": "Principal Island voice for text 200"
    },
    {
      "type": "creative_labs_audio",
      "game": "LBA1",
      "description": "Principal Island voice for text 201"
    },
    {
      "type": "creative_labs_audio",
      "game": "LBA1",
      "description": "Principal Island voice for text 202"
    },
    {
      "type": "creative_labs_audio",
      "game": "LBA1",
      "description": "Principal Island voice for text 203"
    },
    {
      "type": "creative_labs_audio",
      "game": "LBA1",
      "description": "Principal Island voice for text 204"
    },
    {
      "type": "creative_labs_audio",
      "game": "LBA1",
      "description": "Principal Island voice for text 205"
    },
    {
      "type": "creative_labs_audio",
      "game": "LBA1",
      "description": "Principal Island voice for text 206"
    },
    {
      "type": "creative_labs_audio",
      "game": "LBA1",
      "description": "Principal Island voice for text 207"
    },
    {
      "type": "creative_labs_audio",
      "game": "LBA1",
      "description": "Principal Island voice for text 208"
    },
    {
      "type": "creative_labs_audio",
      "game": "LBA1",
      "description": "Principal Island voice for text 209"
    },
    {
      "type": "creative_labs_audio",
      "game": "LBA1",
      "description": "Principal Island voice for text 210"
    },
    {
      "type": "creative_labs_audio",
      "game": "LBA1",
      "description": "Principal Island voice for text 211"
    },
    {
      "type": "creative_labs_audio",
      "game": "LBA1",
      "description": "Principal Island voice for text 212"
    },
    {
      "type": "creative_labs_audio",
      "game": "LBA1",
      "description": "Principal Island voice for text 213"
    },
    {
      "type": "creative_labs_audio",
      "game": "LBA1",
      "description": "Principal Island voice for text 214"
    },
    {
      "type": "creative_labs_audio",
      "game": "LBA1",
      "description": "Principal Island voice for text 215"
    },
    {
      "type": "creative_labs_audio",
      "game": "LBA1",
      "description": "Principal Island voice for text 216"
    },
    {
      "type": "creative_labs_audio",
      "game": "LBA1",
      "description": "Principal Island voice for text 217"
    },
    {
      "type": "creative_labs_audio",
      "game": "LBA1",
      "description": "Principal Island voice for text 218"
    },
    {
      "type": "creative_labs_audio",
      "game": "LBA1",
      "description": "Principal Island voice for text 219"
    },
    {
      "type": "creative_labs_audio",
      "game": "LBA1",
      "description": "Principal Island voice for text 220"
    },
    {
      "type": "creative_labs_audio",
      "game": "LBA1",
      "description": "Principal Island voice for text 221"
    },
    {
      "type": "creative_labs_audio",
      "game": "LBA1",
      "description": "Principal Island voice for text 222"
    },
    {
      "type": "creative_labs_audio",
      "game": "LBA1",
      "description": "Principal Island voice for text 223"
    },
    {
      "type": "creative_labs_audio",
      "game": "LBA1",
      "description": "Principal Island voice for text 224"
    },
    {
      "type": "creative_labs_audio",
      "game": "LBA1",
      "description": "Principal Island voice for text 225"
    },
    {
      "type": "creative_labs_audio",
      "game": "LBA1",
      "description": "Principal Island voice for text 226"
    },
    {
      "type": "creative_labs_audio",
      "game": "LBA1",
      "description": "Principal Island voice for text 227"
    },
    {
      "type": "creative_labs_audio",
      "game": "LBA1",
      "description": "Principal Island voice for text 228"
    },
    {
      "type": "creative_labs_audio",
      "game": "LBA1",
      "description": "Principal Island voice for text 229"
    },
    {
      "type": "creative_labs_audio",
      "game": "LBA1",
      "description": "Principal Island voice for text 230"
    },
    {
      "type": "creative_labs_audio",
      "game": "LBA1",
      "description": "Principal Island voice for text 231"
    },
    {
      "type": "creative_labs_audio",
      "game": "LBA1",
      "description": "Principal Island voice for text 232"
    },
    {
      "type": "creative_labs_audio",
      "game": "LBA1",
      "description": "Principal Island voice for text 233"
    },
    {
      "type": "creative_labs_audio",
      "game": "LBA1",
      "description": "Principal Island voice for text 234"
    },
    {
      "type": "creative_labs_audio",
      "game": "LBA1",
      "description": "Principal Island voice for text 235"
    },
    {
      "type": "creative_labs_audio",
      "game": "LBA1",
      "description": "Principal Island voice for text 236"
    },
    {
      "type": "creative_labs_audio",
      "game": "LBA1",
      "description": "Principal Island voice for text 237"
    },
    {
      "type": "creative_labs_audio",
      "game": "LBA1",
      "description": "Principal Island voice for text 238"
    },
    {
      "type": "creative_labs_audio",
      "game": "LBA1",
      "description": "Principal Island voice for text 239"
    },
    {
      "type": "creative_labs_audio",
      "game": "LBA1",
      "description": "Principal Island voice for text 240"
    },
    {
      "type": "creative_labs_audio",
      "game": "LBA1",
      "description": "Principal Island voice for text 241"
    },
    {
      "type": "creative_labs_audio",
      "game": "LBA1",
      "description": "Principal Island voice for text 242"
    },
    {
      "type": "creative_labs_audio",
      "game": "LBA1",
      "description": "Principal Island voice for text 243"
    },
    {
      "type": "creative_labs_audio",
      "game": "LBA1",
      "description": "Principal Island voice for text 244"
    },
    {
      "type": "creative_labs_audio",
      "game": "LBA1",
      "description": "Principal Island voice for text 245"
    },
    {
      "type": "creative_labs_audio",
      "game": "LBA1",
      "description": "Principal Island voice for text 246"
    },
    {
      "type": "creative_labs_audio",
      "game": "LBA1",
      "description": "Principal Island voice for text 247"
    },
    {
      "type": "creative_labs_audio",
      "game": "LBA1",
      "description": "Principal Island voice for text 248"
    },
    {
      "type": "creative_labs_audio",
      "game": "LBA1",
      "description": "Principal Island voice for text 249"
    },
    {
      "type": "creative_labs_audio",
      "game": "LBA1",
      "description": "Principal Island voice for text 250"
    },
    {
      "type": "creative_labs_audio",
      "game": "LBA1",
      "description": "Principal Island voice for text 251"
    },
    {
      "type": "creative_labs_audio",
      "game": "LBA1",
      "description": "Principal Island voice for text 252"
    },
    {
      "type": "creative_labs_audio",
      "game": "LBA1",
      "description": "Principal Island voice for text 253"
    },
    {
      "type": "creative_labs_audio",
      "game": "LBA1",
      "description": "Principal Island voice for text 254"
    },
    {
      "type": "creative_labs_audio",
      "game": "LBA1",
      "description": "Principal Island voice for text 255"
    },
    {
      "type": "creative_labs_audio",
      "game": "LBA1",
      "description": "Principal Island voice for text 256"
    },
    {
      "type": "creative_labs_audio",
      "game": "LBA1",
      "description": "Principal Island voice for text 257"
    },
    {
      "type": "creative_labs_audio",
      "game": "LBA1",
      "description": "Principal Island voice for text 258"
    },
    {
      "type": "creative_labs_audio",
      "game": "LBA1",
      "description": "Principal Island voice for text 259"
    },
    {
      "type": "creative_labs_audio",
      "game": "LBA1",
      "description": "Principal Island voice for text 260"
    },
    {
      "type": "creative_labs_audio",
      "game": "LBA1",
      "description": "Principal Island voice for text 261"
    },
    {
      "type": "creative_labs_audio",
      "game": "LBA1",
      "description": "Principal Island voice for text 262"
    },
    {
      "type": "creative_labs_audio",
      "game": "LBA1",
      "description": "Principal Island voice for text 263"
    },
    {
      "type": "creative_labs_audio",
      "game": "LBA1",
      "description": "Principal Island voice for text 264"
    },
    {
      "type": "creative_labs_audio",
      "game": "LBA1",
      "description": "Principal Island voice for text 265"
    },
    {
      "type": "creative_labs_audio",
      "game": "LBA1",
      "description": "Principal Island voice for text 266"
    },
    {
      "type": "creative_labs_audio",
      "game": "LBA1",
      "description": "Principal Island voice for text 267"
    }
  ]
}